zep_autogen/__init__.py
zep_autogen/exceptions.py
zep_autogen/graph_memory.py
zep_autogen/memory.py
zep_autogen/tools.py
zep_autogen-1.1.0.dist-info/METADATA
zep_autogen-1.1.0.dist-info/WHEEL
zep_autogen-1.1.0.dist-info/RECORD
