Metadata-Version: 2.4
Name: zep-autogen
Version: 1.1.0
Summary: Autogen integration for Zep
Project-URL: Homepage, https://github.com/getzep/zep
Project-URL: Documentation, https://help.getzep.com/integrations/autogen
Project-URL: Repository, https://github.com/getzep/zep
Project-URL: Bug Tracker, https://github.com/getzep/zep/issues
Project-URL: Changelog, https://github.com/getzep/zep/blob/main/integrations/python/autogen/CHANGELOG.md
Requires-Python: >=3.10
Requires-Dist: aiohttp>=3.8.0
Requires-Dist: autogen-agentchat>=0.6.1
Requires-Dist: autogen-ext[azure,openai]>=0.6.1
Requires-Dist: azure-identity>=1.23.0
Requires-Dist: python-dotenv>=1.0.0
Requires-Dist: python-slugify>=8.0.4
Requires-Dist: rich>=14.0.0
Requires-Dist: zep-cloud>=3.3.0
Provides-Extra: dev
Requires-Dist: mypy>=1.0.0; extra == 'dev'
Requires-Dist: pytest-asyncio; extra == 'dev'
Requires-Dist: pytest-cov; extra == 'dev'
Requires-Dist: pytest>=7.0.0; extra == 'dev'
Requires-Dist: ruff>=0.1.0; extra == 'dev'
